{
	"Device": {
		"ID": "DSE-Queenbreaker02A",
		"Activator": "24199|dse-display-model.esp",
		"Ghost": "29798|dse-display-model.esp",
		"Inventory": "24197|dse-display-model.esp",
		"UpdateFreqUsed": 6.0,
		"Actors": [
			{
				"Name": "The Queen",
				"Package": "24195|dse-display-model.esp",
				"Pos": [ 0.0, 0.0, 0.0 ],
				"HeadTracking": false,
				"Arousing": 1,
				"Equips": [],
				"Objects": [
					{ "Form": "24200|dse-display-model.esp" }
				]
			}
		],
		"ObjectsIdle": [

		],
		"ObjectsUsed": [

		]
	}
}